lython_basic/__init__.py
lython_basic/auth.py
lython_basic/chat.py
lython_basic/codingbat_urls.csv
lython_basic/db.py
lython_basic/rag_chat.py
lython_basic/schema.sql
lython_basic/static/style.css
lython_basic/templates/base.html
lython_basic/templates/auth/login.html
lython_basic/templates/auth/register.html
lython_basic/templates/chat/history.html
lython_basic/templates/chat/index.html
lython_basic/templates/rag_chat/rag_chat.html
lython_basic-1.0.3.dist-info/WHEEL
lython_basic-1.0.3.dist-info/METADATA
lython_basic-1.0.3.dist-info/RECORD
