Metadata-Version: 2.1
Name: lython_basic
Version: 1.0.3
Summary: A Flask application for learning and interacting with Python concepts.
Author-email: Richard Pointing <rpointing97@gmail.com>
Requires-Python: >=3.8
Classifier: Programming Language :: Python :: 3
Classifier: License :: OSI Approved :: MIT License
Classifier: Operating System :: OS Independent
Requires-Dist: flask
Project-URL: Homepage, https://github.com/mr-pointing/Lython_GCU
